{
  "id": "phrasebook-householdchores",
  "name": "Household Chores",
  "description": "Phrasebook for Household Chores",
  "entries": [
    {
      "id": "pb_householdchores_0_0",
      "word": "Haven't you washed the dishes yet?",
      "translation": "Ты ещё не помыл посуду?",
      "language": "en"
    },
    {
      "id": "pb_householdchores_0_1",
      "word": "I hung up the laundry.",
      "translation": "Я повесил бельё.",
      "language": "en"
    },
    {
      "id": "pb_householdchores_0_2",
      "word": "Tom did the laundry.",
      "translation": "Том устроил стирку.",
      "language": "en"
    },
    {
      "id": "pb_householdchores_0_3",
      "word": "Take the garbage out.",
      "translation": "Вынеси мусор.",
      "language": "en"
    },
    {
      "id": "pb_householdchores_0_4",
      "word": "Tom is washing dishes.",
      "translation": "Том моет посуду.",
      "language": "en"
    },
    {
      "id": "pb_householdchores_0_5",
      "word": "No one likes doing laundry.",
      "translation": "Никто не любит стирать.",
      "language": "en"
    },
    {
      "id": "pb_householdchores_0_6",
      "word": "I've almost finished washing the dishes.",
      "translation": "Я почти домыла посуду.",
      "language": "en"
    },
    {
      "id": "pb_householdchores_0_7",
      "word": "Everything here is covered in dust.",
      "translation": "Здесь всё покрыто пылью.",
      "language": "en"
    },
    {
      "id": "pb_householdchores_0_8",
      "word": "I was just doing the dishes.",
      "translation": "Я только мыл посуду.",
      "language": "en"
    },
    {
      "id": "pb_householdchores_0_9",
      "word": "This vacuum cleaner makes a lot of noise.",
      "translation": "Этот пылесос делает много шума.",
      "language": "en"
    },
    {
      "id": "pb_householdchores_0_10",
      "word": "All the desks were covered with dust.",
      "translation": "Все столы были покрыты пылью.",
      "language": "en"
    },
    {
      "id": "pb_householdchores_0_11",
      "word": "Tom has just finished washing dishes.",
      "translation": "Том только что закончил мыть посуду.",
      "language": "en"
    },
    {
      "id": "pb_householdchores_0_12",
      "word": "After eating supper, I washed the dishes.",
      "translation": "Поужинав, я помыл посуду.",
      "language": "en"
    },
    {
      "id": "pb_householdchores_0_13",
      "word": "We hung up the laundry.",
      "translation": "Мы развесили бельё.",
      "language": "en"
    },
    {
      "id": "pb_householdchores_0_14",
      "word": "This vase is made of iron.",
      "translation": "Эта ваза сделана из железа.",
      "language": "en"
    },
    {
      "id": "pb_householdchores_0_15",
      "word": "Don't throw trash here.",
      "translation": "Не бросайте здесь мусор.",
      "language": "en"
    },
    {
      "id": "pb_householdchores_0_16",
      "word": "Did you find this in the trash?",
      "translation": "Ты нашёл это в помойке?",
      "language": "en"
    },
    {
      "id": "pb_householdchores_0_17",
      "word": "Tom threw the apple core into the garbage can.",
      "translation": "Том выбросил яблочный огрызок в мусорный бак.",
      "language": "en"
    },
    {
      "id": "pb_householdchores_0_18",
      "word": "It wasn't Tom who washed the dishes. It was Mary.",
      "translation": "Посуду помыл не Том, а Мэри.",
      "language": "en"
    },
    {
      "id": "pb_householdchores_0_19",
      "word": "Everything is covered with dust.",
      "translation": "Всё покрыто пылью.",
      "language": "en"
    },
    {
      "id": "pb_householdchores_0_20",
      "word": "Throw it out with the rest of the garbage.",
      "translation": "Выбросьте это вместе с остальным мусором.",
      "language": "en"
    },
    {
      "id": "pb_householdchores_0_21",
      "word": "How old is this vacuum cleaner?",
      "translation": "Сколько лет этому пылесосу?",
      "language": "en"
    },
    {
      "id": "pb_householdchores_0_22",
      "word": "Who hung up the laundry?",
      "translation": "Кто вешал бельё?",
      "language": "en"
    },
    {
      "id": "pb_householdchores_0_23",
      "word": "I dried the dishes.",
      "translation": "Я вытер посуду.",
      "language": "en"
    },
    {
      "id": "pb_householdchores_0_24",
      "word": "Have you taken out the garbage?",
      "translation": "Ты вынес мусор?",
      "language": "en"
    },
    {
      "id": "pb_householdchores_0_25",
      "word": "I'll do the dishes.",
      "translation": "Я помою посуду.",
      "language": "en"
    },
    {
      "id": "pb_householdchores_0_26",
      "word": "Tom has a waffle iron.",
      "translation": "У Тома есть вафельница.",
      "language": "en"
    },
    {
      "id": "pb_householdchores_0_27",
      "word": "This is rubbish.",
      "translation": "Это мусор.",
      "language": "en"
    },
    {
      "id": "pb_householdchores_0_28",
      "word": "Tom rinsed the dishes.",
      "translation": "Том ополоснул посуду.",
      "language": "en"
    },
    {
      "id": "pb_householdchores_0_29",
      "word": "There's a lot of dust in the air.",
      "translation": "В воздухе много пыли.",
      "language": "en"
    },
    {
      "id": "pb_householdchores_0_30",
      "word": "She bought a vacuum cleaner at the supermarket.",
      "translation": "Она купила пылесос в супермаркете.",
      "language": "en"
    },
    {
      "id": "pb_householdchores_0_31",
      "word": "This vacuum cleaner is awfully loud.",
      "translation": "Этот пылесос ужасно шумный.",
      "language": "en"
    },
    {
      "id": "pb_householdchores_0_32",
      "word": "A tramp is rummaging through the garbage can.",
      "translation": "Бродяга роется в мусорном баке.",
      "language": "en"
    },
    {
      "id": "pb_householdchores_0_33",
      "word": "I often leave dirty dishes in the sink.",
      "translation": "Я часто оставляю в раковине грязную посуду.",
      "language": "en"
    },
    {
      "id": "pb_householdchores_0_34",
      "word": "He can bend an iron rod with his hands.",
      "translation": "Он может голыми руками согнуть железный прут.",
      "language": "en"
    },
    {
      "id": "pb_householdchores_0_35",
      "word": "I've just finished washing the dishes.",
      "translation": "Я только что закончил мыть посуду.",
      "language": "en"
    },
    {
      "id": "pb_householdchores_0_36",
      "word": "I've already taken out the garbage.",
      "translation": "Я уже вынес мусор.",
      "language": "en"
    },
    {
      "id": "pb_householdchores_0_37",
      "word": "Tom kicked the trash can.",
      "translation": "Том пнул ногой мусорную урну.",
      "language": "en"
    },
    {
      "id": "pb_householdchores_0_38",
      "word": "Tom seldom washes the dishes.",
      "translation": "Том редко моет посуду.",
      "language": "en"
    },
    {
      "id": "pb_householdchores_0_39",
      "word": "Tom is doing the laundry.",
      "translation": "Том занимается стиркой.",
      "language": "en"
    },
    {
      "id": "pb_householdchores_0_40",
      "word": "Are the dishes done?",
      "translation": "Посуда помыта?",
      "language": "en"
    },
    {
      "id": "pb_householdchores_0_41",
      "word": "We need to dust the desk.",
      "translation": "Нам надо протереть стол.",
      "language": "en"
    },
    {
      "id": "pb_householdchores_0_42",
      "word": "The dishes need to be washed.",
      "translation": "Нужно помыть посуду.",
      "language": "en"
    },
    {
      "id": "pb_householdchores_0_43",
      "word": "I need to do the dishes.",
      "translation": "Мне надо помыть посуду.",
      "language": "en"
    },
    {
      "id": "pb_householdchores_0_44",
      "word": "She put the dirty dishes in the sink.",
      "translation": "Она положила грязную посуду в раковину.",
      "language": "en"
    },
    {
      "id": "pb_householdchores_0_45",
      "word": "I do the laundry on Sundays.",
      "translation": "Я стираю по воскресеньям.",
      "language": "en"
    },
    {
      "id": "pb_householdchores_0_46",
      "word": "When we're done eating, I'll do the dishes.",
      "translation": "Когда мы поедим, я помою посуду.",
      "language": "en"
    },
    {
      "id": "pb_householdchores_0_47",
      "word": "Don't talk rubbish.",
      "translation": "Не говори ерунды.",
      "language": "en"
    },
    {
      "id": "pb_householdchores_0_48",
      "word": "There's a lot of dust in the attic.",
      "translation": "На чердаке куча пыли.",
      "language": "en"
    },
    {
      "id": "pb_householdchores_0_49",
      "word": "We're out of laundry detergent.",
      "translation": "У нас закончился стиральный порошок.",
      "language": "en"
    },
    {
      "id": "pb_householdchores_1_0",
      "word": "Onions can be used in many dishes.",
      "translation": "Лук может использоваться во многих блюдах.",
      "language": "en"
    },
    {
      "id": "pb_householdchores_1_1",
      "word": "Tom finished doing the dishes.",
      "translation": "Том домыл посуду.",
      "language": "en"
    },
    {
      "id": "pb_householdchores_1_2",
      "word": "Tom broke the dishes.",
      "translation": "Том разбил посуду.",
      "language": "en"
    },
    {
      "id": "pb_householdchores_1_3",
      "word": "Tom checked all the trash cans.",
      "translation": "Том проверил все мусорные баки.",
      "language": "en"
    },
    {
      "id": "pb_householdchores_1_4",
      "word": "I've already hung up the laundry.",
      "translation": "Я уже повесил бельё.",
      "language": "en"
    },
    {
      "id": "pb_householdchores_1_5",
      "word": "The trash can is empty.",
      "translation": "В мусорном ведре пусто.",
      "language": "en"
    },
    {
      "id": "pb_householdchores_1_6",
      "word": "I'm trying to tidy things up a bit.",
      "translation": "Я пытаюсь мало-мальски привести вещи в порядок.",
      "language": "en"
    },
    {
      "id": "pb_householdchores_1_7",
      "word": "Where's the laundry basket?",
      "translation": "Где корзина для белья?",
      "language": "en"
    },
    {
      "id": "pb_householdchores_1_8",
      "word": "Tom helped Mary with the laundry.",
      "translation": "Том помог Мэри со стиркой.",
      "language": "en"
    },
    {
      "id": "pb_householdchores_1_9",
      "word": "Fold the napkins and put one by each plate.",
      "translation": "Согни салфетки и положи у каждой тарелки по одной.",
      "language": "en"
    },
    {
      "id": "pb_householdchores_1_10",
      "word": "Fold the towels.",
      "translation": "Сложи полотенца.",
      "language": "en"
    },
    {
      "id": "pb_householdchores_1_11",
      "word": "The trash can was empty.",
      "translation": "Мусорное ведро было пустым.",
      "language": "en"
    },
    {
      "id": "pb_householdchores_1_12",
      "word": "Tom is doing laundry.",
      "translation": "Том стирает.",
      "language": "en"
    },
    {
      "id": "pb_householdchores_1_13",
      "word": "I haven't yet washed the dishes.",
      "translation": "Я ещё не помыл посуду.",
      "language": "en"
    },
    {
      "id": "pb_householdchores_1_14",
      "word": "Tom asked Mary to throw the rotten apple into the garbage.",
      "translation": "Том попросил Мэри выкинуть гнилое яблоко в ведро.",
      "language": "en"
    },
    {
      "id": "pb_householdchores_1_15",
      "word": "Put your dirty dishes in the sink.",
      "translation": "Поставь грязную посуду в раковину.",
      "language": "en"
    },
    {
      "id": "pb_householdchores_1_16",
      "word": "I unplugged the iron.",
      "translation": "Я отключил утюг.",
      "language": "en"
    },
    {
      "id": "pb_householdchores_1_17",
      "word": "Iron transmits heat well.",
      "translation": "Железо хорошо передаёт тепло.",
      "language": "en"
    },
    {
      "id": "pb_householdchores_1_18",
      "word": "Fold the blanket.",
      "translation": "Сложи одеяло.",
      "language": "en"
    },
    {
      "id": "pb_householdchores_1_19",
      "word": "I don't want to take the garbage out.",
      "translation": "Я не хочу выносить мусор.",
      "language": "en"
    },
    {
      "id": "pb_householdchores_1_20",
      "word": "The trash can is full.",
      "translation": "Мусорное ведро полное.",
      "language": "en"
    },
    {
      "id": "pb_householdchores_1_21",
      "word": "I don't want to do the dishes.",
      "translation": "Я не хочу мыть посуду.",
      "language": "en"
    },
    {
      "id": "pb_householdchores_1_22",
      "word": "Tom washed the dishes.",
      "translation": "Том помыл посуду.",
      "language": "en"
    },
    {
      "id": "pb_householdchores_1_23",
      "word": "Tom tossed the rotten apple into the garbage can.",
      "translation": "Том бросил гнилое яблоко в мусорное ведро.",
      "language": "en"
    },
    {
      "id": "pb_householdchores_1_24",
      "word": "I'm washing the dishes.",
      "translation": "Я мою посуду.",
      "language": "en"
    },
    {
      "id": "pb_householdchores_1_25",
      "word": "This dust is impossible to filter from the air.",
      "translation": "Эту пыль невозможно отфильтровать из воздуха.",
      "language": "en"
    },
    {
      "id": "pb_householdchores_1_26",
      "word": "The desk is covered with dust.",
      "translation": "Письменный стол покрыт пылью.",
      "language": "en"
    },
    {
      "id": "pb_householdchores_1_27",
      "word": "I did the dishes.",
      "translation": "Я помыл посуду.",
      "language": "en"
    },
    {
      "id": "pb_householdchores_1_28",
      "word": "I need more iron in my diet.",
      "translation": "Мне нужна диета с более высоким содержанием железа.",
      "language": "en"
    },
    {
      "id": "pb_householdchores_1_29",
      "word": "Have you finished washing the dishes?",
      "translation": "Ты домыл посуду?",
      "language": "en"
    },
    {
      "id": "pb_householdchores_1_30",
      "word": "It was me that took out the garbage.",
      "translation": "Мусор вынес я.",
      "language": "en"
    },
    {
      "id": "pb_householdchores_1_31",
      "word": "Tom won't do the dishes.",
      "translation": "Том не будет мыть посуду.",
      "language": "en"
    },
    {
      "id": "pb_householdchores_1_32",
      "word": "Is this made of iron?",
      "translation": "Это из железа?",
      "language": "en"
    },
    {
      "id": "pb_householdchores_1_33",
      "word": "Tom took the trash out.",
      "translation": "Том вынес мусор.",
      "language": "en"
    },
    {
      "id": "pb_householdchores_1_34",
      "word": "Iron these shirts first.",
      "translation": "Погладь сначала эти рубашки.",
      "language": "en"
    },
    {
      "id": "pb_householdchores_1_35",
      "word": "Is the laundry dry yet?",
      "translation": "Бельё уже высохло?",
      "language": "en"
    },
    {
      "id": "pb_householdchores_1_36",
      "word": "Is it made of iron?",
      "translation": "Это сделано из железа?",
      "language": "en"
    },
    {
      "id": "pb_householdchores_1_37",
      "word": "Tom wants you to take the garbage out.",
      "translation": "Том хочет, чтобы ты вынес мусор.",
      "language": "en"
    },
    {
      "id": "pb_householdchores_1_38",
      "word": "Tom is drying the dishes.",
      "translation": "Том вытирает посуду.",
      "language": "en"
    },
    {
      "id": "pb_householdchores_1_39",
      "word": "We took the trash out.",
      "translation": "Мы вынесли мусор.",
      "language": "en"
    },
    {
      "id": "pb_householdchores_1_40",
      "word": "Tom is a chimney sweep.",
      "translation": "Том — трубочист.",
      "language": "en"
    },
    {
      "id": "pb_householdchores_1_41",
      "word": "Its principal exports are iron ore, rubber, diamonds, and gold.",
      "translation": "Её основные статьи экспорта — железная руда, каучук, алмазы и золото.",
      "language": "en"
    },
    {
      "id": "pb_householdchores_1_42",
      "word": "Could you hang up the laundry?",
      "translation": "Ты не мог бы повесить бельё?",
      "language": "en"
    },
    {
      "id": "pb_householdchores_1_43",
      "word": "Iron isn't as valuable as gold.",
      "translation": "Железо не такое ценное, как золото.",
      "language": "en"
    },
    {
      "id": "pb_householdchores_1_44",
      "word": "I haven't washed the dishes.",
      "translation": "Я не помыл посуду.",
      "language": "en"
    },
    {
      "id": "pb_householdchores_1_45",
      "word": "Let's do the dishes.",
      "translation": "Давайте помоем посуду.",
      "language": "en"
    },
    {
      "id": "pb_householdchores_1_46",
      "word": "She took the tablecloths to the laundry.",
      "translation": "Она отнесла скатерти в прачечную.",
      "language": "en"
    },
    {
      "id": "pb_householdchores_1_47",
      "word": "I forgot to remind Tom to take out the garbage.",
      "translation": "Я забыл напомнить Тому, чтобы он вынес мусор.",
      "language": "en"
    },
    {
      "id": "pb_householdchores_1_48",
      "word": "Mary keeps her best dishes in that cabinet.",
      "translation": "Мэри держит свою лучшую посуду в этом шкафу.",
      "language": "en"
    },
    {
      "id": "pb_householdchores_1_49",
      "word": "I've just washed the dishes.",
      "translation": "Я только что помыл посуду.",
      "language": "en"
    },
    {
      "id": "pb_householdchores_2_0",
      "word": "Don't hang up the laundry yet.",
      "translation": "Не вешай пока бельё.",
      "language": "en"
    },
    {
      "id": "pb_householdchores_2_1",
      "word": "We hung up the laundry together.",
      "translation": "Мы вешали бельё вместе.",
      "language": "en"
    },
    {
      "id": "pb_householdchores_2_2",
      "word": "Tom is in the kitchen, washing dishes.",
      "translation": "Том на кухне, моет посуду.",
      "language": "en"
    },
    {
      "id": "pb_householdchores_2_3",
      "word": "A magnet attracts iron.",
      "translation": "Магнит притягивает железо.",
      "language": "en"
    },
    {
      "id": "pb_householdchores_2_4",
      "word": "This is garbage.",
      "translation": "Это мусор.",
      "language": "en"
    },
    {
      "id": "pb_householdchores_2_5",
      "word": "Where is the laundry?",
      "translation": "Где прачечная?",
      "language": "en"
    },
    {
      "id": "pb_householdchores_2_6",
      "word": "I've just finished doing the dishes.",
      "translation": "Я только что закончил мыть посуду.",
      "language": "en"
    },
    {
      "id": "pb_householdchores_2_7",
      "word": "The soldiers are wearing iron helmets.",
      "translation": "Солдаты носят железные каски.",
      "language": "en"
    },
    {
      "id": "pb_householdchores_2_8",
      "word": "Tom unplugged the iron.",
      "translation": "Том выдернул утюг из розетки.",
      "language": "en"
    },
    {
      "id": "pb_householdchores_2_9",
      "word": "The platform was strewn with trash.",
      "translation": "Перрон был усеян мусором.",
      "language": "en"
    },
    {
      "id": "pb_householdchores_2_10",
      "word": "I want you to take the garbage out.",
      "translation": "Я хочу, чтобы ты вынес мусор.",
      "language": "en"
    },
    {
      "id": "pb_householdchores_2_11",
      "word": "Was Tom the one who hung up the laundry?",
      "translation": "Это Том бельё повесил?",
      "language": "en"
    },
    {
      "id": "pb_householdchores_2_12",
      "word": "Do we have a soldering iron?",
      "translation": "У нас паяльник есть?",
      "language": "en"
    },
    {
      "id": "pb_householdchores_2_13",
      "word": "Tom is washing the dishes now.",
      "translation": "Том сейчас моет тарелки.",
      "language": "en"
    },
    {
      "id": "pb_householdchores_2_14",
      "word": "Tom didn't do the dishes.",
      "translation": "Том не помыл посуду.",
      "language": "en"
    },
    {
      "id": "pb_householdchores_2_15",
      "word": "Tom burns all his trash in a barrel in his backyard.",
      "translation": "Том сжигает весь свой мусор в бочке на заднем дворе.",
      "language": "en"
    },
    {
      "id": "pb_householdchores_2_16",
      "word": "Tom washes the dishes.",
      "translation": "Том моет посуду.",
      "language": "en"
    },
    {
      "id": "pb_householdchores_2_17",
      "word": "Tom finished washing the dishes.",
      "translation": "Том домыл посуду.",
      "language": "en"
    },
    {
      "id": "pb_householdchores_2_18",
      "word": "I got this vacuum cleaner for nothing.",
      "translation": "Мне этот пылесос достался бесплатно.",
      "language": "en"
    },
    {
      "id": "pb_householdchores_2_19",
      "word": "Throw it in the trash.",
      "translation": "Выброси его в помойку.",
      "language": "en"
    },
    {
      "id": "pb_householdchores_2_20",
      "word": "Did you do the dishes?",
      "translation": "Вы помыли посуду?",
      "language": "en"
    },
    {
      "id": "pb_householdchores_2_21",
      "word": "Tom put the dirty dishes in the sink.",
      "translation": "Том положил грязную посуду в раковину.",
      "language": "en"
    },
    {
      "id": "pb_householdchores_2_22",
      "word": "Don't air your dirty laundry in public.",
      "translation": "Не выноси сор из избы.",
      "language": "en"
    },
    {
      "id": "pb_householdchores_2_23",
      "word": "Our fence is made of iron.",
      "translation": "Наш забор сделан из железа.",
      "language": "en"
    },
    {
      "id": "pb_householdchores_2_24",
      "word": "Tom took the garbage out.",
      "translation": "Том вынес мусор.",
      "language": "en"
    },
    {
      "id": "pb_householdchores_2_25",
      "word": "They knew how to make iron.",
      "translation": "Они умели обрабатывать железо.",
      "language": "en"
    },
    {
      "id": "pb_householdchores_2_26",
      "word": "I've already washed the dishes.",
      "translation": "Я уже помыл посуду.",
      "language": "en"
    },
    {
      "id": "pb_householdchores_2_27",
      "word": "Gold is heavier than iron.",
      "translation": "Золото тяжелее железа.",
      "language": "en"
    },
    {
      "id": "pb_householdchores_2_28",
      "word": "I broke a glass when I did the dishes.",
      "translation": "Я разбил стакан, когда мыл посуду.",
      "language": "en"
    },
    {
      "id": "pb_householdchores_2_29",
      "word": "Sweep the terrace.",
      "translation": "Подмети террасу.",
      "language": "en"
    },
    {
      "id": "pb_householdchores_2_30",
      "word": "The desk was covered with dust.",
      "translation": "Стол был покрыт пылью.",
      "language": "en"
    },
    {
      "id": "pb_householdchores_2_31",
      "word": "Thanks for doing the dishes.",
      "translation": "Спасибо, что помыл посуду.",
      "language": "en"
    },
    {
      "id": "pb_householdchores_2_32",
      "word": "Fold up your bedding.",
      "translation": "Убери свою постель.",
      "language": "en"
    },
    {
      "id": "pb_householdchores_2_33",
      "word": "Where's your laundry detergent?",
      "translation": "Где у тебя стиральный порошок?",
      "language": "en"
    },
    {
      "id": "pb_householdchores_2_34",
      "word": "Our objective is twofold.",
      "translation": "У нас двойная цель.",
      "language": "en"
    },
    {
      "id": "pb_householdchores_2_35",
      "word": "Do the dishes.",
      "translation": "Помой посуду.",
      "language": "en"
    },
    {
      "id": "pb_householdchores_2_36",
      "word": "I have to take out the trash.",
      "translation": "Мне надо вынести мусор.",
      "language": "en"
    },
    {
      "id": "pb_householdchores_2_37",
      "word": "Tom forgot to take out the garbage.",
      "translation": "Том забыл вынести мусор.",
      "language": "en"
    },
    {
      "id": "pb_householdchores_2_38",
      "word": "It was all covered with dust.",
      "translation": "Он весь был покрыт пылью.",
      "language": "en"
    },
    {
      "id": "pb_householdchores_2_39",
      "word": "There's so much dust here.",
      "translation": "Сколько здесь пыли!",
      "language": "en"
    },
    {
      "id": "pb_householdchores_2_40",
      "word": "I haven't done the dishes yet.",
      "translation": "Я ещё не помыл посуду.",
      "language": "en"
    },
    {
      "id": "pb_householdchores_2_41",
      "word": "The laundry is still damp.",
      "translation": "Бельё ещё влажное.",
      "language": "en"
    },
    {
      "id": "pb_householdchores_2_42",
      "word": "The dishes were manufactured in Taiwan.",
      "translation": "Тарелки были произведены на Тайване.",
      "language": "en"
    },
    {
      "id": "pb_householdchores_2_43",
      "word": "Have you done the laundry?",
      "translation": "Ты постирала бельё?",
      "language": "en"
    },
    {
      "id": "pb_householdchores_2_44",
      "word": "The laundry isn't dry yet.",
      "translation": "Бельё ещё не высохло.",
      "language": "en"
    },
    {
      "id": "pb_householdchores_2_45",
      "word": "This is iron.",
      "translation": "Это железо.",
      "language": "en"
    },
    {
      "id": "pb_householdchores_2_46",
      "word": "I didn't do the dishes.",
      "translation": "Я не помыл посуду.",
      "language": "en"
    },
    {
      "id": "pb_householdchores_2_47",
      "word": "Iron is used in ship construction.",
      "translation": "Железо используется в кораблестроении.",
      "language": "en"
    },
    {
      "id": "pb_householdchores_2_48",
      "word": "The parts are connected by an iron rod.",
      "translation": "Эти части соединены железным стержнем.",
      "language": "en"
    },
    {
      "id": "pb_householdchores_2_49",
      "word": "Laundry is a chore.",
      "translation": "Стирка - рутинная работа.",
      "language": "en"
    },
    {
      "id": "pb_householdchores_3_0",
      "word": "I'm doing my laundry.",
      "translation": "Я стираю.",
      "language": "en"
    },
    {
      "id": "pb_householdchores_3_1",
      "word": "I was the one who washed the dishes.",
      "translation": "Это я мыла посуду.",
      "language": "en"
    },
    {
      "id": "pb_householdchores_3_2",
      "word": "Can't you vacuum later?",
      "translation": "Ты не можешь попылесосить попозже?",
      "language": "en"
    },
    {
      "id": "pb_householdchores_3_3",
      "word": "I need a soldering iron.",
      "translation": "Мне нужен паяльник.",
      "language": "en"
    },
    {
      "id": "pb_householdchores_3_4",
      "word": "Garbage in, garbage out.",
      "translation": "Что посеешь - то пожнёшь.",
      "language": "en"
    },
    {
      "id": "pb_householdchores_3_5",
      "word": "Do we have an iron?",
      "translation": "У нас есть утюг?",
      "language": "en"
    },
    {
      "id": "pb_householdchores_3_6",
      "word": "The dishes need to be done.",
      "translation": "Нужно помыть посуду.",
      "language": "en"
    },
    {
      "id": "pb_householdchores_3_7",
      "word": "The dishes are piling up in the sink.",
      "translation": "Посуда скапливается в раковине.",
      "language": "en"
    },
    {
      "id": "pb_householdchores_3_8",
      "word": "Tom removed my blindfold.",
      "translation": "Том снял повязку с моих глаз.",
      "language": "en"
    },
    {
      "id": "pb_householdchores_3_9",
      "word": "Nobody likes to do laundry.",
      "translation": "Никому не нравится заниматься стиркой.",
      "language": "en"
    },
    {
      "id": "pb_householdchores_3_10",
      "word": "The ladder was covered with dust and rust.",
      "translation": "Лестница была покрыта пылью и ржавчиной.",
      "language": "en"
    },
    {
      "id": "pb_householdchores_3_11",
      "word": "Dust had accumulated on the desk.",
      "translation": "На столе скопилась пыль.",
      "language": "en"
    },
    {
      "id": "pb_householdchores_3_12",
      "word": "Tom wanted Mary to take out the garbage.",
      "translation": "Том хотел, чтобы Мэри вынесла мусор.",
      "language": "en"
    },
    {
      "id": "pb_householdchores_3_13",
      "word": "Can you get this trash out of here?",
      "translation": "Ты можешь вынести отсюда этот мусор?",
      "language": "en"
    },
    {
      "id": "pb_householdchores_3_14",
      "word": "Thanks for washing the dishes.",
      "translation": "Спасибо, что помыл посуду.",
      "language": "en"
    },
    {
      "id": "pb_householdchores_3_15",
      "word": "A dust storm is coming.",
      "translation": "Приближается пыльная буря.",
      "language": "en"
    },
    {
      "id": "pb_householdchores_3_16",
      "word": "Fold the paper in the middle.",
      "translation": "Сложите листок посередине.",
      "language": "en"
    },
    {
      "id": "pb_householdchores_3_17",
      "word": "Do you have laundry to do?",
      "translation": "У вас есть что постирать?",
      "language": "en"
    },
    {
      "id": "pb_householdchores_3_18",
      "word": "The desk was covered in dust.",
      "translation": "Стол был покрыт пылью.",
      "language": "en"
    },
    {
      "id": "pb_householdchores_3_19",
      "word": "I'm washing dishes.",
      "translation": "Я мою посуду.",
      "language": "en"
    },
    {
      "id": "pb_householdchores_3_20",
      "word": "Did you iron all the shirts?",
      "translation": "Вы все рубашки погладили?",
      "language": "en"
    },
    {
      "id": "pb_householdchores_3_21",
      "word": "I'm the one who takes out the garbage.",
      "translation": "Это я выношу мусор.",
      "language": "en"
    },
    {
      "id": "pb_householdchores_3_22",
      "word": "She was washing the dishes then.",
      "translation": "В это время она мыла посуду.",
      "language": "en"
    },
    {
      "id": "pb_householdchores_3_23",
      "word": "Tom was untidy.",
      "translation": "Том был неряшлив.",
      "language": "en"
    },
    {
      "id": "pb_householdchores_3_24",
      "word": "Washing dishes is something I don't really enjoy doing.",
      "translation": "Мытье посуды совсем не доставляет мне удовольствия.",
      "language": "en"
    },
    {
      "id": "pb_householdchores_3_25",
      "word": "I'm doing the dishes.",
      "translation": "Я мою посуду.",
      "language": "en"
    },
    {
      "id": "pb_householdchores_3_26",
      "word": "The whole framework was made of iron.",
      "translation": "Каркас был целиком сделан из железа.",
      "language": "en"
    },
    {
      "id": "pb_householdchores_3_27",
      "word": "Is my laundry ready?",
      "translation": "Моя стирка готова?",
      "language": "en"
    },
    {
      "id": "pb_householdchores_3_28",
      "word": "Gold's heavier than iron.",
      "translation": "Золото тяжелее железа.",
      "language": "en"
    },
    {
      "id": "pb_householdchores_3_29",
      "word": "I broke three dishes.",
      "translation": "Я разбил три тарелки.",
      "language": "en"
    },
    {
      "id": "pb_householdchores_3_30",
      "word": "Tom is tidy.",
      "translation": "Том аккуратный.",
      "language": "en"
    },
    {
      "id": "pb_householdchores_3_31",
      "word": "Tom drives a garbage truck.",
      "translation": "Том водит мусоровоз.",
      "language": "en"
    },
    {
      "id": "pb_householdchores_3_32",
      "word": "Tom is doing the dishes.",
      "translation": "Том моет посуду.",
      "language": "en"
    },
    {
      "id": "pb_householdchores_3_33",
      "word": "Chocolate has more iron than spinach.",
      "translation": "В шоколаде больше железа, чем в шпинате.",
      "language": "en"
    },
    {
      "id": "pb_householdchores_3_34",
      "word": "Tom helped with the dishes.",
      "translation": "Том помог с посудой.",
      "language": "en"
    },
    {
      "id": "pb_householdchores_3_35",
      "word": "I folded the laundry.",
      "translation": "Я сложил бельё.",
      "language": "en"
    },
    {
      "id": "pb_householdchores_3_36",
      "word": "Tom wants you to take out the garbage.",
      "translation": "Том хочет, чтобы ты вынес мусор.",
      "language": "en"
    },
    {
      "id": "pb_householdchores_3_37",
      "word": "The old iron pipe was full of rust.",
      "translation": "Старая железная труба полностью проржавела.",
      "language": "en"
    },
    {
      "id": "pb_householdchores_3_38",
      "word": "I want you to take out the garbage.",
      "translation": "Я хочу, чтобы ты вынес мусор.",
      "language": "en"
    },
    {
      "id": "pb_householdchores_3_39",
      "word": "I've already taken out the trash.",
      "translation": "Я уже вынес мусор.",
      "language": "en"
    },
    {
      "id": "pb_householdchores_3_40",
      "word": "She brushed away the dust.",
      "translation": "Она вытерла пыль.",
      "language": "en"
    },
    {
      "id": "pb_householdchores_3_41",
      "word": "The rings around Saturn are made up of dust and ice.",
      "translation": "Кольца вокруг Сатурна состоят из пыли и льда.",
      "language": "en"
    },
    {
      "id": "pb_householdchores_3_42",
      "word": "There was a stack of dirty dishes in the sink.",
      "translation": "В раковине была гора грязной посуды.",
      "language": "en"
    },
    {
      "id": "pb_householdchores_3_43",
      "word": "She has just finished washing dishes.",
      "translation": "Она только что закончила мыть посуду.",
      "language": "en"
    },
    {
      "id": "pb_householdchores_3_44",
      "word": "The laundry can wait.",
      "translation": "Стирка может подождать.",
      "language": "en"
    },
    {
      "id": "pb_householdchores_3_45",
      "word": "Pick up your trash.",
      "translation": "Подбери свой мусор.",
      "language": "en"
    },
    {
      "id": "pb_householdchores_3_46",
      "word": "There are dirty dishes in the sink.",
      "translation": "В раковине грязные тарелки.",
      "language": "en"
    },
    {
      "id": "pb_householdchores_3_47",
      "word": "Were you the one who washed the dishes?",
      "translation": "Это ты посуду помыл?",
      "language": "en"
    },
    {
      "id": "pb_householdchores_3_48",
      "word": "Fold the paper in half.",
      "translation": "Сложи лист бумаги пополам.",
      "language": "en"
    },
    {
      "id": "pb_householdchores_3_49",
      "word": "Tom and Mary washed the dishes together.",
      "translation": "Том и Мэри вместе помыли посуду.",
      "language": "en"
    },
    {
      "id": "pb_householdchores_4_0",
      "word": "Tom broke three dishes.",
      "translation": "Том разбил три тарелки.",
      "language": "en"
    },
    {
      "id": "pb_householdchores_4_1",
      "word": "Garbage was everywhere.",
      "translation": "Повсюду был мусор.",
      "language": "en"
    },
    {
      "id": "pb_householdchores_4_2",
      "word": "We've got to get rid of all this trash.",
      "translation": "Нам надо избавиться от всего этого мусора.",
      "language": "en"
    },
    {
      "id": "pb_householdchores_4_3",
      "word": "After eating dinner, I washed the dishes.",
      "translation": "Поужинав, я помыл посуду.",
      "language": "en"
    },
    {
      "id": "pb_householdchores_4_4",
      "word": "I washed the dishes.",
      "translation": "Я помыл посуду.",
      "language": "en"
    },
    {
      "id": "pb_householdchores_4_5",
      "word": "I've already taken the garbage out.",
      "translation": "Я уже вынес мусор.",
      "language": "en"
    },
    {
      "id": "pb_householdchores_4_6",
      "word": "I told Tom to take out the garbage.",
      "translation": "Я сказал Тому вынести мусор.",
      "language": "en"
    },
    {
      "id": "pb_householdchores_4_7",
      "word": "Iron is more useful than gold.",
      "translation": "Железо полезнее, чем золото.",
      "language": "en"
    },
    {
      "id": "pb_householdchores_4_8",
      "word": "Gold is more valuable than iron.",
      "translation": "Золото ценится больше, чем железо.",
      "language": "en"
    },
    {
      "id": "pb_householdchores_4_9",
      "word": "Didn't I tell you to take out the garbage?",
      "translation": "Разве я не говорил тебе вынести мусор?",
      "language": "en"
    },
    {
      "id": "pb_householdchores_4_10",
      "word": "Take out the trash.",
      "translation": "Вынеси мусор!",
      "language": "en"
    },
    {
      "id": "pb_householdchores_4_11",
      "word": "Tom did the dishes for Mary.",
      "translation": "Том вымыл посуду для Мэри.",
      "language": "en"
    },
    {
      "id": "pb_householdchores_4_12",
      "word": "The dishes are done.",
      "translation": "Посуда помыта.",
      "language": "en"
    },
    {
      "id": "pb_householdchores_4_13",
      "word": "Tom is untidy.",
      "translation": "Том неопрятный.",
      "language": "en"
    },
    {
      "id": "pb_householdchores_4_14",
      "word": "Don't forget to take out the garbage.",
      "translation": "Не забудь выбросить мусор.",
      "language": "en"
    },
    {
      "id": "pb_householdchores_4_15",
      "word": "Can you do the dishes?",
      "translation": "Можешь помыть посуду?",
      "language": "en"
    },
    {
      "id": "pb_householdchores_4_16",
      "word": "Tom got Mary to take out the garbage.",
      "translation": "Том попросил Мэри вынести мусор.",
      "language": "en"
    },
    {
      "id": "pb_householdchores_4_17",
      "word": "She used a damp rag to wipe off the dust.",
      "translation": "Она воспользовалась влажной тряпкой, чтобы вытереть пыль.",
      "language": "en"
    },
    {
      "id": "pb_householdchores_4_18",
      "word": "Tom asked Mary to take out the garbage.",
      "translation": "Том попросил Мэри вынести мусор.",
      "language": "en"
    },
    {
      "id": "pb_householdchores_4_19",
      "word": "The sink was full of dirty dishes.",
      "translation": "Раковина была полна грязной посуды.",
      "language": "en"
    },
    {
      "id": "pb_householdchores_4_20",
      "word": "She explained to me that we throw away too much garbage.",
      "translation": "Она объяснила мне, что мы выбрасываем слишком много мусора.",
      "language": "en"
    },
    {
      "id": "pb_householdchores_4_21",
      "word": "Tom needs to do the dishes.",
      "translation": "Тому надо помыть посуду.",
      "language": "en"
    },
    {
      "id": "pb_householdchores_4_22",
      "word": "Just sweep it under the rug.",
      "translation": "Просто замети это под коврик.",
      "language": "en"
    },
    {
      "id": "pb_householdchores_4_23",
      "word": "Tom is a garbage collector.",
      "translation": "Том — сборщик мусора.",
      "language": "en"
    },
    {
      "id": "pb_householdchores_4_24",
      "word": "The sink is full of dirty dishes.",
      "translation": "Раковина полна грязной посуды.",
      "language": "en"
    },
    {
      "id": "pb_householdchores_4_25",
      "word": "Tom helped Mary fold the laundry.",
      "translation": "Том помог Мэри сложить белье.",
      "language": "en"
    },
    {
      "id": "pb_householdchores_4_26",
      "word": "Gold is more precious than iron.",
      "translation": "Золото ценнее железа.",
      "language": "en"
    },
    {
      "id": "pb_householdchores_4_27",
      "word": "Who's doing the dishes?",
      "translation": "Кто будет мыть посуду?",
      "language": "en"
    },
    {
      "id": "pb_householdchores_4_28",
      "word": "Have you washed the dishes?",
      "translation": "Вы помыли посуду?",
      "language": "en"
    },
    {
      "id": "pb_householdchores_4_29",
      "word": "Tom is going to do the dishes.",
      "translation": "Том помоет посуду.",
      "language": "en"
    },
    {
      "id": "pb_householdchores_4_30",
      "word": "Dust got into one of my eyes.",
      "translation": "Пыль попала мне в глаз.",
      "language": "en"
    },
    {
      "id": "pb_householdchores_4_31",
      "word": "Tom helped Mary fold the blankets.",
      "translation": "Том помог Мэри сложить одеяла.",
      "language": "en"
    },
    {
      "id": "pb_householdchores_4_32",
      "word": "I'll hang up the laundry.",
      "translation": "Я повешу бельё.",
      "language": "en"
    },
    {
      "id": "pb_householdchores_4_33",
      "word": "Tom sorted his laundry.",
      "translation": "Том разобрал бельё для стирки.",
      "language": "en"
    },
    {
      "id": "pb_householdchores_4_34",
      "word": "Tom turned on the soldering iron.",
      "translation": "Том включил паяльник.",
      "language": "en"
    },
    {
      "id": "pb_householdchores_4_35",
      "word": "Glasses and dishes were broken.",
      "translation": "Бокалы и блюда были разбиты.",
      "language": "en"
    },
    {
      "id": "pb_householdchores_4_36",
      "word": "Tom is washing the dishes.",
      "translation": "Том моет посуду.",
      "language": "en"
    },
    {
      "id": "pb_householdchores_4_37",
      "word": "After supper, I washed the dishes.",
      "translation": "Поужинав, я помыл посуду.",
      "language": "en"
    },
    {
      "id": "pb_householdchores_4_38",
      "word": "I haven't washed the dishes yet.",
      "translation": "Я ещё не помыл посуду.",
      "language": "en"
    },
    {
      "id": "pb_householdchores_4_39",
      "word": "Iron is harder than gold.",
      "translation": "Железо твёрже, чем золото.",
      "language": "en"
    },
    {
      "id": "pb_householdchores_4_40",
      "word": "Iron is much more useful than gold.",
      "translation": "Железо гораздо полезнее золота.",
      "language": "en"
    },
    {
      "id": "pb_householdchores_4_41",
      "word": "Why are you eating this garbage?",
      "translation": "Почему вы едите эту дрянь?",
      "language": "en"
    },
    {
      "id": "pb_householdchores_4_42",
      "word": "We didn't do the dishes.",
      "translation": "Мы не мыли посуду.",
      "language": "en"
    },
    {
      "id": "pb_householdchores_4_43",
      "word": "Put all the rubbish in the barrel.",
      "translation": "Положите весь мусор в эту бочку.",
      "language": "en"
    },
    {
      "id": "pb_householdchores_4_44",
      "word": "She was washing the dishes.",
      "translation": "Она мыла посуду.",
      "language": "en"
    },
    {
      "id": "pb_householdchores_4_45",
      "word": "Have you washed the dishes yet?",
      "translation": "Ты уже помыл посуду?",
      "language": "en"
    },
    {
      "id": "pb_householdchores_4_46",
      "word": "We did the dishes.",
      "translation": "Мы мыли посуду.",
      "language": "en"
    },
    {
      "id": "pb_householdchores_4_47",
      "word": "I'm not the one who takes out the garbage.",
      "translation": "Мусор выношу не я.",
      "language": "en"
    }
  ]
}